hass_mqtt_devices/Notes.dev.md
hass_mqtt_devices/__init__.py
hass_mqtt_devices/cli/__init__.py
hass_mqtt_devices/cli/device_driver.py
hass_mqtt_devices/cli/main_driver.py
hass_mqtt_devices/cli/sensors.py
hass_mqtt_devices/device.py
hass_mqtt_devices/sensors.py
hass_mqtt_devices/settings.py
hass_mqtt_devices/utils.py
hass_mqtt_devices-0.2.1.dist-info/entry_points.txt
hass_mqtt_devices-0.2.1.dist-info/LICENSE
hass_mqtt_devices-0.2.1.dist-info/WHEEL
hass_mqtt_devices-0.2.1.dist-info/METADATA
hass_mqtt_devices-0.2.1.dist-info/RECORD
