Metadata-Version: 2.1
Name: hass-mqtt-devices
Version: 0.2.1
Summary: 
Author: Joe Block
Author-email: jpb@unixorn.net
Requires-Python: >=3.9,<4.0
Classifier: Programming Language :: Python :: 3
Classifier: Programming Language :: Python :: 3.9
Classifier: Programming Language :: Python :: 3.10
Classifier: Programming Language :: Python :: 3.11
Requires-Dist: gitlike-commands (>=0.2.1,<0.3.0)
Requires-Dist: paho-mqtt (>=1.6.1,<2.0.0)
Requires-Dist: pyaml (>=21.10.1,<22.0.0)
Requires-Dist: thelogrus (>=0.7.0,<0.8.0)
